text_snippet_summarizer/__init__.py
text_snippet_summarizer/main.py
text_snippet_summarizer/prompts.py
text_snippet_summarizer-2025.12.21113112.dist-info/METADATA
text_snippet_summarizer-2025.12.21113112.dist-info/WHEEL
text_snippet_summarizer-2025.12.21113112.dist-info/top_level.txt
text_snippet_summarizer-2025.12.21113112.dist-info/RECORD
