Metadata-Version: 2.4
Name: text-snippet-summarizer
Version: 2025.12.21113112
Summary: A new package facilitates extracting a concise, structured summary from user-provided news headlines or brief texts by utilizing pattern matching and LLM interactions. This tool aims to help researche
Author-email: text-snippet-summarizer <hi@eugene.plus>
License: MIT
Project-URL: Homepage, https://github.com/chigwell/text-snippet-summarizer
Requires-Python: >=3.9
Requires-Dist: langchain-llm7>=0.0.0
Requires-Dist: llmatch-messages>=0.0.0
Requires-Dist: langchain-core>=0.3.0
